{
  "resourceType": "MedicationKnowledge",
  "id": "insulin-lispro",
  "meta": {
    "lastUpdated": "2026-03-03T10:40:32Z"
  },
  "status": "active",
  "code": {
    "coding": [
      {
        "system": "https://www.drugbank.ca/drugs",
        "code": "DB00046",
        "display": "INSULIN LISPRO"
      },
      {
        "system": "https://eutxgnn.yao.care/drugs",
        "code": "insulin-lispro",
        "display": "Lyumjev (previously Liumjev)"
      }
    ],
    "text": "Lyumjev (previously Liumjev) (INSULIN LISPRO)"
  },
  "intendedJurisdiction": [
    {
      "coding": [
        {
          "system": "urn:iso:std:iso:3166",
          "code": "EU",
          "display": "European Union"
        }
      ]
    }
  ],
  "synonym": [
    "Lyumjev (previously Liumjev)"
  ],
  "extension": [
    {
      "url": "https://eutxgnn.yao.care/fhir/StructureDefinition/ema-product-number",
      "valueString": "EMEA/H/C/005037"
    },
    {
      "url": "https://eutxgnn.yao.care/fhir/StructureDefinition/evidence-level",
      "valueCode": "L5"
    }
  ]
}